MANIFEST.in
readme.rst
setup.py
blockdiagcontrib/__init__.py
blockdiagcontrib/tex.py
blockdiagcontrib_tex.egg-info/PKG-INFO
blockdiagcontrib_tex.egg-info/SOURCES.txt
blockdiagcontrib_tex.egg-info/dependency_links.txt
blockdiagcontrib_tex.egg-info/entry_points.txt
blockdiagcontrib_tex.egg-info/requires.txt
blockdiagcontrib_tex.egg-info/top_level.txt