Metadata-Version: 1.1
Name: blockdiagcontrib-tex
Version: 0.2.2
Summary: TeX plugin for blockdiag
Home-page: https://bitbucket.org/yassu0320/blockdiagcontrib-tex
Author: Yassu 0320
Author-email: mathyassu at gmail.com
License: Apache License 2.0
Keywords: diagram,generator
Platform: UNKNOWN
Classifier: Development Status :: 4 - Beta
Classifier: Intended Audience :: System Administrators
Classifier: License :: OSI Approved :: Apache Software License
Classifier: Programming Language :: Python
Classifier: Programming Language :: Python :: 3.2
Classifier: Programming Language :: Python :: 3.3
Classifier: Programming Language :: Python :: 3.4
Classifier: Topic :: Software Development
Classifier: Topic :: Software Development :: Documentation
Classifier: Topic :: Text Processing :: Markup
